gallerist/__init__.py
gallerist/abc.py
gallerist/core.py
gallerist/fs.py
gallerist-0.0.6.dist-info/LICENSE
gallerist-0.0.6.dist-info/METADATA
gallerist-0.0.6.dist-info/WHEEL
gallerist-0.0.6.dist-info/top_level.txt
gallerist-0.0.6.dist-info/RECORD
