Metadata-Version: 2.1
Name: gallerist
Version: 0.0.6
Summary: Classes and methods to handle pictures for the web
Home-page: https://github.com/Neoteroi/Gallerist
Author: RobertoPrevato
Author-email: roberto.prevato@gmail.com
License: MIT
Keywords: pictures images web
Platform: UNKNOWN
Classifier: Development Status :: 5 - Production/Stable
Classifier: License :: OSI Approved :: MIT License
Classifier: Programming Language :: Python :: 3
Classifier: Programming Language :: Python :: 3.6
Classifier: Programming Language :: Python :: 3.7
Classifier: Programming Language :: Python :: 3.8
Classifier: Programming Language :: Python :: 3.9
Classifier: Programming Language :: Python :: 3.10
Classifier: Operating System :: OS Independent
License-File: LICENSE
Requires-Dist: aiofiles (>=0.4.0)
Requires-Dist: Pillow (>=8.3.2)
